en_core_web_sm/__init__.py
en_core_web_sm/meta.json
en_core_web_sm/en_core_web_sm-2.2.5/accuracy.json
en_core_web_sm/en_core_web_sm-2.2.5/meta.json
en_core_web_sm/en_core_web_sm-2.2.5/tokenizer
en_core_web_sm/en_core_web_sm-2.2.5/ner/cfg
en_core_web_sm/en_core_web_sm-2.2.5/ner/model
en_core_web_sm/en_core_web_sm-2.2.5/ner/moves
en_core_web_sm/en_core_web_sm-2.2.5/parser/cfg
en_core_web_sm/en_core_web_sm-2.2.5/parser/model
en_core_web_sm/en_core_web_sm-2.2.5/parser/moves
en_core_web_sm/en_core_web_sm-2.2.5/tagger/cfg
en_core_web_sm/en_core_web_sm-2.2.5/tagger/model
en_core_web_sm/en_core_web_sm-2.2.5/tagger/tag_map
en_core_web_sm/en_core_web_sm-2.2.5/vocab/key2row
en_core_web_sm/en_core_web_sm-2.2.5/vocab/lexemes.bin
en_core_web_sm/en_core_web_sm-2.2.5/vocab/lookups.bin
en_core_web_sm/en_core_web_sm-2.2.5/vocab/strings.json
en_core_web_sm/en_core_web_sm-2.2.5/vocab/vectors
en_core_web_sm_mirror-2.2.5.dist-info/METADATA
en_core_web_sm_mirror-2.2.5.dist-info/WHEEL
en_core_web_sm_mirror-2.2.5.dist-info/top_level.txt
en_core_web_sm_mirror-2.2.5.dist-info/RECORD
