Metadata-Version: 2.1
Name: en-core-web-sm-mirror
Version: 2.2.5
Summary: English multi-task CNN trained on OntoNotes. Assigns context-specific token vectors, POS tags, dependency parse and named entities.
Home-page: https://explosion.ai
Author: Explosion
Author-email: contact@explosion.ai
License: MIT
Platform: UNKNOWN
Requires-Dist: spacy (>=2.2.2)
